aiogram_widgets/__meta__.py
aiogram_widgets/classes.py
aiogram_widgets/enums.py
aiogram_widgets/pagination/__init__.py
aiogram_widgets/pagination/_base.py
aiogram_widgets/pagination/keyboard.py
aiogram_widgets/pagination/text.py
aiogram_widgets/types.py
aiogram_widgets-1.2.7.dist-info/LICENSE
aiogram_widgets-1.2.7.dist-info/METADATA
aiogram_widgets-1.2.7.dist-info/WHEEL
aiogram_widgets-1.2.7.dist-info/RECORD
