Metadata-Version: 2.1
Name: aiogram-widgets
Version: 1.2.7
Summary: Create most popular widgets for aiogram 3 in few code lines 
Keywords: aiogram,telegram api,pagination,calendar,checkbox,multiselect,templates
Author: ggindinson
Requires-Python: >=3.9,<4.0
Classifier: License :: OSI Approved :: MIT License
Classifier: Operating System :: OS Independent
Classifier: Programming Language :: Python :: 3
Classifier: Programming Language :: Python :: 3.9
Classifier: Programming Language :: Python :: 3.10
Classifier: Programming Language :: Python :: 3.11
Requires-Dist: aiogram (>=3.0.0b1)
Requires-Dist: pydantic (>=1.10.4)
